pydouyu/__init__.py
pydouyu/client.py
pydouyu/heartbeat_worker.py
pydouyu/message_consumer.py
pydouyu/message_worker.py
pydouyu/packet_util.py
pydouyu/tcp_socket.py
pydouyu-0.0.7.dist-info/LICENSE
pydouyu-0.0.7.dist-info/METADATA
pydouyu-0.0.7.dist-info/WHEEL
pydouyu-0.0.7.dist-info/top_level.txt
pydouyu-0.0.7.dist-info/RECORD
